ddeint/__init__.py
ddeint/ddeint.py
ddeint-0.3.0.dist-info/LICENSE
ddeint-0.3.0.dist-info/METADATA
ddeint-0.3.0.dist-info/WHEEL
ddeint-0.3.0.dist-info/top_level.txt
ddeint-0.3.0.dist-info/RECORD
