Metadata-Version: 2.1
Name: ddeint
Version: 0.3.0
Summary: Scipy-based Delay Differential Equations solver
Author: Zulko
License: CCO
Project-URL: Homepage, https://github.com/zulko/ddeint
Project-URL: Changelog, https://github.com/zulko/ddeint/releases
Project-URL: Issues, https://github.com/zulko/ddeint/issues
Project-URL: CI, https://github.com/zulko/ddeint/actions
Requires-Python: >=3.8
License-File: LICENSE
Requires-Dist: numpy
Requires-Dist: scipy
Provides-Extra: test
Requires-Dist: pytest ; extra == 'test'
